{
  "generated": "2026-06-13T05:02:06.609314+00:00",
  "period": {
    "ga4": {
      "start": "2026-05-14",
      "end": "2026-06-12"
    },
    "ga4Prev": {
      "start": "2026-04-14",
      "end": "2026-05-13"
    },
    "gsc": {
      "start": "2026-05-16",
      "end": "2026-06-12"
    }
  },
  "ga4": {
    "summary": {
      "sessions": 309,
      "totalUsers": 224,
      "pageviews": 427,
      "avgSessionDurationSec": 125.1,
      "avgBounceRatePct": 68.8
    },
    "previousPeriod": {
      "sessions": 0,
      "totalUsers": 0,
      "pageviews": 0,
      "avgSessionDurationSec": 0,
      "avgBounceRatePct": 0
    },
    "daily": [
      {
        "date": "20260612",
        "sessions": "58",
        "totalUsers": "47",
        "screenPageViews": "81",
        "averageSessionDuration": "215.38224665517242",
        "bounceRate": "1"
      },
      {
        "date": "20260602",
        "sessions": "42",
        "totalUsers": "30",
        "screenPageViews": "69",
        "averageSessionDuration": "214.33099209523812",
        "bounceRate": "0.66666666666666663"
      },
      {
        "date": "20260603",
        "sessions": "35",
        "totalUsers": "27",
        "screenPageViews": "41",
        "averageSessionDuration": "72.4662057142857",
        "bounceRate": "0.62857142857142856"
      },
      {
        "date": "20260605",
        "sessions": "33",
        "totalUsers": "25",
        "screenPageViews": "47",
        "averageSessionDuration": "10.915916969696969",
        "bounceRate": "0.63636363636363635"
      },
      {
        "date": "20260609",
        "sessions": "32",
        "totalUsers": "21",
        "screenPageViews": "48",
        "averageSessionDuration": "79.06788378125",
        "bounceRate": "0.625"
      },
      {
        "date": "20260608",
        "sessions": "23",
        "totalUsers": "16",
        "screenPageViews": "27",
        "averageSessionDuration": "49.003774652173917",
        "bounceRate": "0.69565217391304346"
      },
      {
        "date": "20260604",
        "sessions": "22",
        "totalUsers": "13",
        "screenPageViews": "25",
        "averageSessionDuration": "122.14850295454545",
        "bounceRate": "0.68181818181818177"
      },
      {
        "date": "20260610",
        "sessions": "17",
        "totalUsers": "9",
        "screenPageViews": "29",
        "averageSessionDuration": "420.44215805882351",
        "bounceRate": "0.41176470588235292"
      },
      {
        "date": "20260611",
        "sessions": "16",
        "totalUsers": "13",
        "screenPageViews": "22",
        "averageSessionDuration": "168.216747375",
        "bounceRate": "0.5625"
      },
      {
        "date": "20260606",
        "sessions": "13",
        "totalUsers": "10",
        "screenPageViews": "17",
        "averageSessionDuration": "17.201672461538461",
        "bounceRate": "0.61538461538461542"
      },
      {
        "date": "20260607",
        "sessions": "11",
        "totalUsers": "6",
        "screenPageViews": "14",
        "averageSessionDuration": "130.658865",
        "bounceRate": "0.72727272727272729"
      },
      {
        "date": "20260601",
        "sessions": "7",
        "totalUsers": "7",
        "screenPageViews": "7",
        "averageSessionDuration": "1.9267554285714286",
        "bounceRate": "1"
      }
    ],
    "topPages": [
      {
        "pagePath": "/",
        "screenPageViews": "178",
        "sessions": "148",
        "totalUsers": "81"
      },
      {
        "pagePath": "/articles/cannes-lions-women-taking-stage.html",
        "screenPageViews": "46",
        "sessions": "43",
        "totalUsers": "26"
      },
      {
        "pagePath": "/articles/pre-cannes-deal-roundup.html",
        "screenPageViews": "23",
        "sessions": "19",
        "totalUsers": "17"
      },
      {
        "pagePath": "/articles/cannes-3b-networking-failure.html",
        "screenPageViews": "22",
        "sessions": "25",
        "totalUsers": "17"
      },
      {
        "pagePath": "/articles/agriarche-cannes-2026.html",
        "screenPageViews": "16",
        "sessions": "9",
        "totalUsers": "6"
      },
      {
        "pagePath": "/about",
        "screenPageViews": "15",
        "sessions": "22",
        "totalUsers": "8"
      },
      {
        "pagePath": "/about.html",
        "screenPageViews": "13",
        "sessions": "14",
        "totalUsers": "11"
      },
      {
        "pagePath": "/articles/cannes-un-reform-reality-gap.html",
        "screenPageViews": "12",
        "sessions": "13",
        "totalUsers": "13"
      },
      {
        "pagePath": "/articles/un-turns-81-internet-explorer.html",
        "screenPageViews": "12",
        "sessions": "10",
        "totalUsers": "6"
      },
      {
        "pagePath": "/articles/africa-hidden-unicorns.html",
        "screenPageViews": "11",
        "sessions": "11",
        "totalUsers": "7"
      }
    ],
    "topSources": [
      {
        "sessionSource": "(direct)",
        "sessions": "247",
        "totalUsers": "134"
      },
      {
        "sessionSource": "linkedin.com",
        "sessions": "19",
        "totalUsers": "15"
      },
      {
        "sessionSource": "m.facebook.com",
        "sessions": "17",
        "totalUsers": "17"
      },
      {
        "sessionSource": "(not set)",
        "sessions": "16",
        "totalUsers": "13"
      },
      {
        "sessionSource": "facebook.com",
        "sessions": "16",
        "totalUsers": "16"
      },
      {
        "sessionSource": "t.co",
        "sessions": "2",
        "totalUsers": "2"
      },
      {
        "sessionSource": "youtube.com",
        "sessions": "2",
        "totalUsers": "1"
      },
      {
        "sessionSource": "bing",
        "sessions": "1",
        "totalUsers": "1"
      }
    ]
  },
  "gsc": {
    "summary": {
      "clicks": 0,
      "impressions": 0,
      "avgPosition": 0,
      "dataPoints": 0
    },
    "topQueries": [],
    "topPages": [
      {
        "key": "https://theupsidejournal.com/",
        "clicks": 0,
        "impressions": 10,
        "ctr": 0,
        "position": 3.4
      }
    ]
  }
}